{
  "transition_id": "TR_5CDA00F154F4BB6C",
  "parent_run_id": "RC_RBQ90_PBL255_IMPORTED_PACKAGE_PERIOD_TUNED_20225Z0000_BQIC_0611143733_BQIC_0611161228_BQIC_0612060642_BQIC_0612072125",
  "child_run_id": "RC_BQIC_SWAY_0612090051_F100_I102",
  "parent_candidate_id": "RBQ90_PBL255_IMPORTED_PACKAGE_PERIOD_TUNED_20225Z0000_BQIC_0611143733_BQIC_0611161228_BQIC_0612060642_BQIC_0612072125",
  "child_candidate_id": "BQIC_SWAY_0612090051_F100_I102",
  "oracle_id": "oracle_c26754c99eb2607c",
  "epoch_id": "oracle_c26754c99eb2607c",
  "parameter_group": "diagonal_hydro",
  "action_type": "signed_ic_bquad",
  "target_dof": "FD_SWAY",
  "parameter_delta": {
    "hydrodyn_edits": [
      {
        "block": "BQuad",
        "i": 1,
        "j": 1,
        "value": 1125000.0
      }
    ],
    "moordyn": {},
    "initial_conditions": {
      "Sway": -10.169400000000001
    },
    "tmax": 900,
    "decision_meta": {
      "signed_ic_bquad_tune": true,
      "selected_dof_candidates": {
        "FD_SURGE": "RBQ90_PBL255_IMPORTED_PACKAGE_PERIOD_TUNED_20225Z0000_BQIC_0611143733_BQIC_0611161228_BQIC_0612060642",
        "FD_SWAY": "RBQ90_PBL255_IMPORTED_PACKAGE_PERIOD_TUNED_20225Z0000_BQIC_0611143733_BQIC_0611161228_BQIC_0612060642",
        "FD_HEAVE": "RBQ90_PBL255_IMPORTED_PACKAGE_PERIOD_TUNED_20225Z0000_BQIC_0611143733_BQIC_0611161228_BQIC_0612060642",
        "FD_ROLL": "RBQ90_PBL255_IMPORTED_PACKAGE_PERIOD_TUNED_20225Z0000_BQIC_0611143733_BQIC_0611161228_BQIC_0612060642",
        "FD_PITCH": "RBQ90_PBL255_IMPORTED_PACKAGE_PERIOD_TUNED_20225Z0000_BQIC_0611143733_BQIC_0611161228_BQIC_0612060642",
        "FD_YAW": "RBQ90_PBL255_IMPORTED_PACKAGE_PERIOD_TUNED_20225Z0000_BQIC_0611143733_BQIC_0611161228_BQIC_0612060642"
      },
      "bquad_multipliers": {
        "FD_SURGE": 1.0,
        "FD_SWAY": 1.0,
        "FD_HEAVE": 1.0,
        "FD_ROLL": 1.0,
        "FD_PITCH": 1.0,
        "FD_YAW": 1.0
      },
      "signed_initial_conditions": {
        "FD_SURGE": -13.617,
        "FD_SWAY": -9.97,
        "FD_HEAVE": -8.183834704,
        "FD_ROLL": 16.88639943,
        "FD_PITCH": -9.679198059,
        "FD_YAW": -14.975232
      },
      "dof_packages": [
        "FD_HEAVE",
        "FD_PITCH",
        "FD_ROLL",
        "FD_SURGE",
        "FD_SWAY",
        "FD_YAW"
      ],
      "bquad_multiplier": 1.0
    },
    "changed_parameters": "HydroDyn.BQuad[1,1];IC.Sway;FST.TMax"
  },
  "global_score_delta": -0.0012838653043887316,
  "metric_deltas": {
    "FD_SWAY": {
      "score": {
        "parent": 1.1317076896778862,
        "child": 0.8014242053775592,
        "delta": -0.33028348430032695,
        "signed_delta": -0.33028348430032695,
        "comparison": "absolute_error",
        "direction": "improved"
      },
      "period_error_pct": {
        "parent": 1.9047802,
        "child": 2.6066805,
        "delta": 0.7019002999999999,
        "signed_delta": 0.7019002999999999,
        "comparison": "absolute_error",
        "direction": "worsened"
      },
      "envelope_error": {
        "parent": 0.36327972,
        "child": 0.32304132,
        "delta": -0.04023839999999995,
        "signed_delta": -0.04023839999999995,
        "comparison": "absolute_error",
        "direction": "improved"
      },
      "ler_error": {
        "parent": 1.3027659,
        "child": 0.35183958,
        "delta": -0.95092632,
        "signed_delta": -0.95092632,
        "comparison": "absolute_error",
        "direction": "improved"
      },
      "fp_error": {
        "parent": 0.16746894,
        "child": 0.17945897,
        "delta": 0.011990029999999985,
        "signed_delta": 0.011990029999999985,
        "comparison": "absolute_error",
        "direction": "worsened"
      },
      "zeta_error_ratio": {
        "parent": 0.21769698011219327,
        "child": 0.051256817108924685,
        "delta": -0.16644016300326858,
        "signed_delta": -0.16644016300326858,
        "comparison": "absolute_error",
        "direction": "improved"
      }
    }
  },
  "new_failures": [
    "missing_dof",
    "missing_dof:FD_HEAVE",
    "missing_dof:FD_PITCH",
    "missing_dof:FD_ROLL",
    "missing_dof:FD_SURGE",
    "missing_dof:FD_YAW"
  ],
  "resolved_failures": [],
  "step_decision": {
    "status": "EVIDENCE_ONLY",
    "reason": "incomplete suite: 1/6 DOFs have metrics",
    "hard_constraint_violations": [
      "missing_dof:FD_HEAVE",
      "missing_dof:FD_PITCH",
      "missing_dof:FD_ROLL",
      "missing_dof:FD_SURGE",
      "missing_dof:FD_YAW"
    ],
    "tags": [
      "incomplete_suite"
    ]
  },
  "loop_verdict": {
    "status": "RUNNING",
    "reason": "suite incomplete",
    "tags": [
      "incomplete_suite"
    ]
  },
  "source_run_ids": [
    "RC_RBQ90_PBL255_IMPORTED_PACKAGE_PERIOD_TUNED_20225Z0000_BQIC_0611143733_BQIC_0611161228_BQIC_0612060642_BQIC_0612072125",
    "RC_BQIC_SWAY_0612090051_F100_I102"
  ],
  "created_at": "2026-07-07T14:15:15+00:00"
}